credentials_replacer
