Metadata-Version: 1.0
Name: aws-credentials-replacer
Version: 0.1.6
Summary: AWS credentials replacer
Home-page: https://github.com/singleton11/aws-credential-replacer
Author: Anton Prokhorov
Author-email: betrayer11@gmail.com
License: UNKNOWN
Platform: UNKNOWN
